hica/__init__.py
hica/agent.py
hica/cli.py
hica/core.py
hica/logging.py
hica/memory.py
hica/models.py
hica/tools.py
hica-1.2.3.dist-info/METADATA
hica-1.2.3.dist-info/WHEEL
hica-1.2.3.dist-info/entry_points.txt
hica-1.2.3.dist-info/licenses/LICENCE
hica-1.2.3.dist-info/RECORD
