Metadata-Version: 2.4
Name: hica
Version: 1.2.3
Summary: Highly Customizable Agent Library for maximal visibility and control for your Agentic workflows
Author-email: Sandipan Haldar <work@sandipanhaldar.com>
License: MIT
License-File: LICENCE
Requires-Python: >=3.12
Requires-Dist: fastapi
Requires-Dist: fastmcp>=2.10.2
Requires-Dist: instructor
Requires-Dist: jsonref>=1.1.0
Requires-Dist: openai
Requires-Dist: pydantic
Requires-Dist: pydantic-ai
Requires-Dist: pymongo>=4.13.2
Requires-Dist: python-dotenv
Requires-Dist: structlog
Requires-Dist: uvicorn
Provides-Extra: all
Requires-Dist: pytest-asyncio>=0.20; extra == 'all'
Requires-Dist: pytest>=7.0; extra == 'all'
Requires-Dist: requests; extra == 'all'
Requires-Dist: streamlit; extra == 'all'
Requires-Dist: streamlit-autorefresh; extra == 'all'
Provides-Extra: examples
Requires-Dist: requests; extra == 'examples'
Requires-Dist: streamlit; extra == 'examples'
Requires-Dist: streamlit-autorefresh; extra == 'examples'
Provides-Extra: test
Requires-Dist: pytest-asyncio>=0.20; extra == 'test'
Requires-Dist: pytest>=7.0; extra == 'test'
